abdullahadeeb/__init__.py
abdullahadeeb/main.py
abdullahadeeb-0.1.0.dist-info/licenses/LICENSE
abdullahadeeb-0.1.0.dist-info/METADATA
abdullahadeeb-0.1.0.dist-info/WHEEL
abdullahadeeb-0.1.0.dist-info/entry_points.txt
abdullahadeeb-0.1.0.dist-info/top_level.txt
abdullahadeeb-0.1.0.dist-info/RECORD
